optimalgiv/__init__.py
optimalgiv/_bridge.py
optimalgiv/_env_tools.py
optimalgiv/_pca.py
optimalgiv/_simulation.py
optimalgiv-0.2.1.dist-info/licenses/LICENSE
optimalgiv-0.2.1.dist-info/METADATA
optimalgiv-0.2.1.dist-info/WHEEL
optimalgiv-0.2.1.dist-info/top_level.txt
optimalgiv-0.2.1.dist-info/RECORD
