Metadata-Version: 2.4
Name: optimalgiv
Version: 0.2.1
Summary: Python ⇄ Julia bridge for the OptimalGIV package
Author: Marco Zhang
License: MIT License
Project-URL: Source, https://github.com/mArc0v0mag1c/optimalgiv
Requires-Python: >=3.9
License-File: LICENSE
Requires-Dist: pandas>=1.5
Requires-Dist: numpy>=1.22
Requires-Dist: juliacall==0.9.24
Dynamic: license-file
